rabbitbus/__init__.py
rabbitbus/manager.py
rabbitbus/requests.py
rabbitbus/responses.py
rabbitbus/acks/__init__.py
rabbitbus/acks/requests.py
rabbitbus/acks/responses.py
rabbitbus-0.0.7.dist-info/LICENSE
rabbitbus-0.0.7.dist-info/METADATA
rabbitbus-0.0.7.dist-info/WHEEL
rabbitbus-0.0.7.dist-info/top_level.txt
rabbitbus-0.0.7.dist-info/RECORD
