Metadata-Version: 2.1
Name: rabbitbus
Version: 0.0.7
Summary: RabbitMQ app framework
Home-page: http://gitlab.rednvd.ru/krylov/rabbitbus
Author: KrylovYS
Author-email: krylov.ys@malltech.ru
License: MIT
Platform: UNKNOWN
Classifier: License :: OSI Approved :: MIT License
Classifier: Programming Language :: Python
Classifier: Programming Language :: Python :: 3
Classifier: Programming Language :: Python :: 3.6
Classifier: Programming Language :: Python :: Implementation :: CPython
Classifier: Programming Language :: Python :: Implementation :: PyPy
Requires-Python: >=3.6.0
Requires-Dist: aioamqp (==0.14.0)
